{
    "taskDefinitionArn": "arn:aws:ecs:us-east-1:782469701585:task-definition/techmart-task-eastjava-agus:1",
    "containerDefinitions": [
        {
            "name": "techmart-container",
            "image": "782469701585.dkr.ecr.us-east-1.amazonaws.com/techmart-ecr-eastjava-agus",
            "cpu": 0,
            "links": [],
            "portMappings": [
                {
                    "containerPort": 5000,
                    "hostPort": 5000,
                    "protocol": "tcp"
                }
            ],
            "essential": true,
            "entryPoint": [],
            "command": [],
            "environment": [
                {
                    "name": "AWS_SESSION_TOKEN",
                    "value": "<session_token>"
                },
                {
                    "name": "FLASK_DEBUG",
                    "value": "true"
                },
                {
                    "name": "AWS_ACCESS_KEY_ID",
                    "value": "<access_key>"
                },
                {
                    "name": "AWS_SECRET_ACCESS_KEY",
                    "value": "<secrets_access_key>"
                },
                {
                    "name": "FORECAST_API_URL",
                    "value": "https://p3kk33xw5a.execute-api.us-east-1.amazonaws.com/production"
                },
                {
                    "name": "PREDICTION_API_URL",
                    "value": "https://p3kk33xw5a.execute-api.us-east-1.amazonaws.com/production"
                },
                {
                    "name": "FLASK_HOST",
                    "value": "0.0.0.0"
                },
                {
                    "name": "API_GATEWAY_KEY",
                    "value": "TkOSk52FNX9XOwQ4rWbtL5AIIacHfcQW1jjxwihz"
                },
                {
                    "name": "FLASK_PORT",
                    "value": "5000"
                }
            ],
            "environmentFiles": [],
            "mountPoints": [],
            "volumesFrom": [],
            "secrets": [],
            "dnsServers": [],
            "dnsSearchDomains": [],
            "extraHosts": [],
            "dockerSecurityOptions": [],
            "dockerLabels": {},
            "ulimits": [],
            "systemControls": [],
            "credentialSpecs": []
        }
    ],
    "family": "techmart-task-eastjava-agus",
    "executionRoleArn": "arn:aws:iam::782469701585:role/LabRole",
    "networkMode": "awsvpc",
    "revision": 1,
    "volumes": [],
    "status": "ACTIVE",
    "requiresAttributes": [
        {
            "name": "com.amazonaws.ecs.capability.ecr-auth"
        },
        {
            "name": "com.amazonaws.ecs.capability.docker-remote-api.1.17"
        },
        {
            "name": "ecs.capability.execution-role-ecr-pull"
        },
        {
            "name": "com.amazonaws.ecs.capability.docker-remote-api.1.18"
        },
        {
            "name": "ecs.capability.task-eni"
        }
    ],
    "placementConstraints": [],
    "compatibilities": [
        "EC2",
        "MANAGED_INSTANCES",
        "FARGATE"
    ],
    "requiresCompatibilities": [
        "FARGATE"
    ],
    "cpu": "1024",
    "memory": "3072",
    "registeredAt": "2026-02-07T08:30:26.456Z",
    "registeredBy": "arn:aws:sts::782469701585:assumed-role/LabRole/AWSCloudFormation",
    "tags": []
}